notify/__init__.py
notify/models/__init__.py
notify/models/rate_limit.py
notify/models/status.py
line_notify_sdk-1.0.dist-info/LICENSE
line_notify_sdk-1.0.dist-info/METADATA
line_notify_sdk-1.0.dist-info/WHEEL
line_notify_sdk-1.0.dist-info/top_level.txt
line_notify_sdk-1.0.dist-info/RECORD
