Metadata-Version: 2.1
Name: line-notify-sdk
Version: 1.0
Summary: LINE Notify SDK for Pyrhon
Home-page: https://github.com/nanato12/line-notify-sdk
Author: nanato12
Author-email: admin@nanato12.info
Maintainer: nanato12
Maintainer-email: admin@nanato12.info
License: MIT License
Keywords: line line-notify line-notify-sdk
Classifier: License :: OSI Approved :: MIT License
Classifier: Intended Audience :: Developers
Classifier: Programming Language :: Python :: 3
Classifier: Programming Language :: Python :: 3 :: Only
Classifier: Programming Language :: Python :: 3.8
Classifier: Programming Language :: Python :: 3.9
Classifier: Programming Language :: Python :: 3.10
Classifier: Programming Language :: Python :: 3.11
Classifier: Programming Language :: Python :: 3.12
Classifier: Topic :: Software Development
Requires-Python: >=3.8
License-File: LICENSE
Requires-Dist: pydantic>=2.7.1
Requires-Dist: requests>=2.32.2
